{
  "verses": [
    {
      "id": 91,
      "verse_key": "2:84",
      "code_v2": "ﱁ ﱂ ﱃ ﱄ ﱅ ﱆ ﱇ ﱈ ﱉ ﱊ ﱋ ﱌ ﱍ ﱎ ﱏ ﱐ",
      "v2_page": 13
    },
    {
      "id": 92,
      "verse_key": "2:85",
      "code_v2": "ﱑ ﱒ ﱓ ﱔ ﱕ ﱖ ﱗ ﱘ ﱙ ﱚ ﱛ ﱜ ﱝ ﱞ ﱟ ﱠ ﱡ ﱢ ﱣ ﱤ ﱥ ﱦ ﱧ ﱨ ﱩ ﱪ ﱫ ﱬ ﱭ ﱮ ﱯ ﱰ ﱱ ﱲ ﱳ ﱴ ﱵ ﱶ ﱷ ﱸ ﱹ ﱺ ﱻ ﱼ ﱽ ﱾ ﱿ ﲀ ﲁ ﲂ ﲃ ﲄ ﲅ ﲆ",
      "v2_page": 13
    },
    {
      "id": 93,
      "verse_key": "2:86",
      "code_v2": "ﲇ ﲈ ﲉ ﲊ ﲋ ﲌ ﲍ ﲎ ﲏ ﲐ ﲑ ﲒ ﲓ ﲔ ﲕ",
      "v2_page": 13
    },
    {
      "id": 94,
      "verse_key": "2:87",
      "code_v2": "ﲖ ﲗ ﲘ ﲙ ﲚ ﲛ ﲜ ﲝ ﲞ ﲟ ﲠ ﲡ ﲢ ﲣ ﲤ ﲥ ﲦ ﲧ ﲨ ﲩ ﲪ ﲫ ﲬ ﲭ ﲮ ﲯ ﲰ ﲱ ﲲ ﲳ ﲴ",
      "v2_page": 13
    },
    {
      "id": 95,
      "verse_key": "2:88",
      "code_v2": "ﲵ ﲶ ﲷ ﲸ ﲹ ﲺ ﲻ ﲼ ﲽ ﲾ ﲿ ﳀ",
      "v2_page": 13
    }
  ],
  "meta": {
    "filters": {
      "page_number": "13"
    }
  }
}